python_storybook/core/Story.py
python_storybook/core/StoryHub.py
python_storybook/core/StoryManager.py
python_storybook/core/__init__.py
python_storybook/core/config.py
python_storybook/core/utils.py
python_storybook_core-0.1.3.4.dist-info/LICENSE
python_storybook_core-0.1.3.4.dist-info/METADATA
python_storybook_core-0.1.3.4.dist-info/WHEEL
python_storybook_core-0.1.3.4.dist-info/top_level.txt
python_storybook_core-0.1.3.4.dist-info/RECORD
