Metadata-Version: 2.1
Name: python-storybook-core
Version: 0.1.3.4
Summary: Core library for Python-Storybook integration
Author-email: Sisung Kim <sisung.kim1@gmail.com>
Project-URL: Homepage, https://github.com/crimson206/python-storybook-core
Project-URL: Bug Tracker, https://github.com/crimson206/python-storybook-core/issues
Classifier: Programming Language :: Python :: 3
Classifier: Intended Audience :: Developers
Classifier: Topic :: Software Development :: Build Tools
Classifier: License :: OSI Approved :: MIT License
Classifier: Operating System :: OS Independent
Requires-Python: >=3.9
License-File: LICENSE
Requires-Dist: pydantic
